nextrad_client/__init__.py
nextrad_client/__main__.py
nextrad_client/app.py
nextrad_client-1.0.0.dist-info/LICENSE
nextrad_client-1.0.0.dist-info/METADATA
nextrad_client-1.0.0.dist-info/WHEEL
nextrad_client-1.0.0.dist-info/entry_points.txt
nextrad_client-1.0.0.dist-info/top_level.txt
nextrad_client-1.0.0.dist-info/RECORD
