Metadata-Version: 2.1
Name: nextrad-client
Version: 1.0.0
Summary: Interacts with a pedestal device as a controller
Home-page: https://github.com/ZidaanHabib/nextrad-linky-links
Author: Zidaan Habib
Author-email: hbbzid001@myuct.ac.za
License: GNU General Public License v3
Keywords: nextrad
Platform: UNKNOWN
Classifier: Development Status :: 2 - Pre-Alpha
Classifier: Intended Audience :: Developers
Classifier: License :: OSI Approved :: GNU General Public License v3 (GPLv3)
Classifier: Natural Language :: English
Classifier: Programming Language :: Python :: 3.6
Classifier: Programming Language :: Python :: 3.7
Classifier: Programming Language :: Python :: 3.8
Requires-Python: >=3.8
License-File: LICENSE
Requires-Dist: pynmea2
Requires-Dist: paho-mqtt
Requires-Dist: pyserial
